kinto_attachment/__init__.py
kinto_attachment/listeners.py
kinto_attachment/utils.py
kinto_attachment/views.py
kinto_attachment-7.2.0.dist-info/licenses/LICENSE
kinto_attachment-7.2.0.dist-info/METADATA
kinto_attachment-7.2.0.dist-info/WHEEL
kinto_attachment-7.2.0.dist-info/entry_points.txt
kinto_attachment-7.2.0.dist-info/top_level.txt
kinto_attachment-7.2.0.dist-info/RECORD
