Metadata-Version: 2.4
Name: kinto-attachment
Version: 7.2.0
Summary: Attach files to Kinto records
Author-email: Mozilla Services <developers@kinto-storage.org>
License:                                  Apache License
Project-URL: Repository, https://github.com/Kinto/kinto-attachment
Keywords: web services
Classifier: Programming Language :: Python
Classifier: Programming Language :: Python :: 3
Classifier: Topic :: Internet :: WWW/HTTP
Classifier: Topic :: Internet :: WWW/HTTP :: WSGI :: Application
Classifier: License :: OSI Approved :: Apache Software License
License-File: LICENSE
Requires-Dist: boto
Requires-Dist: google-cloud-storage
Requires-Dist: kinto[monitoring]
Requires-Dist: pyramid_storage
Requires-Dist: greenlet>=1
Provides-Extra: dev
Requires-Dist: ruff; extra == "dev"
Requires-Dist: moto[s3,server]<6; extra == "dev"
Requires-Dist: kinto_http; extra == "dev"
Requires-Dist: pytest; extra == "dev"
Requires-Dist: pytest-cache; extra == "dev"
Requires-Dist: pytest-cov; extra == "dev"
Requires-Dist: webtest; extra == "dev"
Requires-Dist: kinto[postgresql]; extra == "dev"
Dynamic: license-file
